tfire/__init__.py
tfire/tfsm_fire.py
tfire/tfsm_gui.py
tfsm_fire-0.1.0.dist-info/METADATA
tfsm_fire-0.1.0.dist-info/WHEEL
tfsm_fire-0.1.0.dist-info/entry_points.txt
tfsm_fire-0.1.0.dist-info/top_level.txt
tfsm_fire-0.1.0.dist-info/RECORD
