Metadata-Version: 2.4
Name: tfsm-fire
Version: 0.1.0
Summary: Automatically find and apply the best TextFSM template for your network device output
Home-page: https://github.com/scottpeterman/tfsm_fire
Author: Scott Peterman
Author-email: scottpeterman@gmail.com
License: GPL-3.0-or-later
Project-URL: Bug Tracker, https://github.com/scottpeterman/tfsm_fire/issues
Project-URL: Source, https://github.com/scottpeterman/tfsm_fire
Keywords: textfsm network automation parsing cisco arista juniper
Classifier: Development Status :: 4 - Beta
Classifier: Environment :: Console
Classifier: Environment :: X11 Applications :: Qt
Classifier: Intended Audience :: System Administrators
Classifier: Intended Audience :: Telecommunications Industry
Classifier: License :: OSI Approved :: GNU General Public License v3 or later (GPLv3+)
Classifier: Operating System :: OS Independent
Classifier: Programming Language :: Python :: 3
Classifier: Programming Language :: Python :: 3.10
Classifier: Programming Language :: Python :: 3.11
Classifier: Programming Language :: Python :: 3.12
Classifier: Topic :: System :: Networking
Classifier: Topic :: System :: Systems Administration
Classifier: Topic :: Text Processing :: Filters
Requires-Python: >=3.10
Requires-Dist: textfsm>=1.1.3
Requires-Dist: click>=8.0
Provides-Extra: gui
Requires-Dist: PyQt6>=6.4; extra == "gui"
Requires-Dist: requests>=2.28; extra == "gui"
Dynamic: author
Dynamic: author-email
Dynamic: classifier
Dynamic: description
Dynamic: description-content-type
Dynamic: home-page
Dynamic: keywords
Dynamic: license
Dynamic: project-url
Dynamic: provides-extra
Dynamic: requires-dist
Dynamic: requires-python
Dynamic: summary
